README.md
setup.cfg
setup.py
sac/__init__.py
sac/util.py
sac.egg-info/PKG-INFO
sac.egg-info/SOURCES.txt
sac.egg-info/dependency_links.txt
sac.egg-info/entry_points.txt
sac.egg-info/requires.txt
sac.egg-info/top_level.txt
sac/cli/__init__.py
sac/cli/wav_editor.py
sac/methods/__init__.py
sac/methods/evaluation.py
sac/methods/peak_detection.py
sac/methods/self_similarity.py
sac/methods/vad.py
sac/methods/sm_analysis/__init__.py
sac/methods/sm_analysis/kernel.py
sac/methods/sm_analysis/region_growing.py
sac/model/__init__.py
sac/model/audacity_label.py
test/test_util.py