Metadata-Version: 1.1
Name: sac
Version: 0.7.0
Summary: Semantic Audio Companion
Home-page: https://github.com/nicktgr15/sac
Author: Nikolaos Tsipas
Author-email: nicktgr15@yahoo.com
License: UNKNOWN
Download-URL: https://github.com/nicktgr15/sac/releases/tag/0.7.0
Keywords: semantic,audio,sox,similarity,matrix
Platform: UNKNOWN
